LscCalculator/NumbersCalculator.py
LscCalculator/StringsCalculator.py
LscCalculator/__init__.py
lsccalculator-0.0.1.dist-info/licenses/LICENSE
lsccalculator-0.0.1.dist-info/METADATA
lsccalculator-0.0.1.dist-info/WHEEL
lsccalculator-0.0.1.dist-info/top_level.txt
lsccalculator-0.0.1.dist-info/RECORD
