Metadata-Version: 2.4
Name: LscCalculator
Version: 0.0.1
Summary: 计算库（整合decimal）
Author-email: Linsc <1344343923@qq.com>
Classifier: Programming Language :: Python :: 3
Classifier: License :: OSI Approved :: MIT License
Classifier: Operating System :: OS Independent
Requires-Python: >=3.12
License-File: LICENSE
Dynamic: license-file
